VERILOG/XOR GATE/4_input_xor.v
module xor_gate(a,b,c,d,y);

input a,b,c,d;
output y;

xor(y,a,b,c,d);

endmodule

XOR GATE/4_input_xor_tb.v
`timescale 1ns/1ps
`include "4_input_xor.v"

module xor_gate_tb;

  reg a, b, c, d;
  wire y;
  
  // Reference (expected output)
  wire y_ref;
  
  // Mismatch signal
  wire mismatch;
  
  // Instantiate DUT (Device Under Test)
  xor_gate uut 
    (
        .a(a),
        .b(b),
        .c(c),
        .d(d),
        .y(y)
    );
    
    // Hardcoded reference logic (same AND behavior)
  assign y_ref = a^b^c^d;
  
  // Mismatch = 1 if output is wrong
  assign mismatch = (y !== y_ref);
  
  initial begin
      $dumpfile("xor_gate.vcd");  // waveform file
      $dumpvars(0, xor_gate_tb);
  
      // Test all cases
      a = 0; b = 0; c = 0; d = 0; #10;
      a = 0; b = 0; c = 0; d = 1; #10;
      a = 0; b = 0; c = 1; d = 0; #10;
      a = 0; b = 0; c = 1; d = 1; #10;
      a = 0; b = 1; c = 0; d = 0; #10;
      a = 0; b = 1; c = 0; d = 1; #10;
      a = 0; b = 1; c = 1; d = 0; #10;
      a = 0; b = 1; c = 1; d = 1; #10;
      a = 1; b = 0; c = 0; d = 0; #10;
      a = 1; b = 0; c = 0; d = 1; #10;
      a = 1; b = 0; c = 1; d = 0; #10;
      a = 1; b = 0; c = 1; d = 1; #10;
      a = 1; b = 1; c = 0; d = 0; #10;
      a = 1; b = 1; c = 0; d = 1; #10;
      a = 1; b = 1; c = 1; d = 0; #10;
      a = 1; b = 1; c = 1; d = 1; #10;
  
      $finish;
  end

endmodule

XOR GATE/xor_gate.vcd
$date
	Thu Apr 23 02:01:12 2026
$end
$version
	Icarus Verilog
$end
$timescale
	1ps
$end
$scope module xor_gate_tb $end
$var wire 1 ! y_ref $end
$var wire 1 " y $end
$var wire 1 # mismatch $end
$var reg 1 $ a $end
$var reg 1 % b $end
$var reg 1 & c $end
$var reg 1 ' d $end
$scope module uut $end
$var wire 1 $ a $end
$var wire 1 % b $end
$var wire 1 & c $end
$var wire 1 ' d $end
$var wire 1 " y $end
$upscope $end
$upscope $end
$enddefinitions $end
$comment Show the parameter values. $end
$dumpall
$end
#0
$dumpvars
0'
0&
0%
0$
0#
0"
0!
$end
#10000
1"
0#
1!
1'
#20000
0'
1&
#30000
0"
0#
0!
1'
#40000
1!
0#
1"
0'
0&
1%
#50000
0"
0#
0!
1'
#60000
0'
1&
#70000
1"
0#
1!
1'
#80000
0'
0&
0%
1$
#90000
0"
0#
0!
1'
#100000
0'
1&
#110000
1"
0#
1!
1'
#120000
0!
0#
0"
0'
0&
1%
#130000
1"
0#
1!
1'
#140000
0'
1&
#150000
0"
0#
0!
1'
